snap_ocr/__init__.py
snap_ocr/__main__.py
snap_ocr/app.py
snap_ocr/config.py
snap_ocr/errors.py
snap_ocr/hotkey.py
snap_ocr/logging_conf.py
snap_ocr/ocr.py
snap_ocr/paths.py
snap_ocr/perm_bootstrap.py
snap_ocr/region_capture.py
snap_ocr/screenshot.py
snap_ocr/tray.py
snap_ocr/util.py
snap_ocr/assets/icon.png
snap_ocr-0.3.1.dist-info/licenses/LICENSE
snap_ocr-0.3.1.dist-info/METADATA
snap_ocr-0.3.1.dist-info/WHEEL
snap_ocr-0.3.1.dist-info/entry_points.txt
snap_ocr-0.3.1.dist-info/top_level.txt
snap_ocr-0.3.1.dist-info/RECORD
