Metadata-Version: 2.4
Name: snap-ocr
Version: 0.3.1
Summary: Background tray utility that screenshots and OCRs in one hotkey press.
Author: Brandon Johnson
License: MIT License
Project-URL: Homepage, https://github.com/jbj0005/snap-ocr
Project-URL: Repository, https://github.com/jbj0005/snap-ocr
Project-URL: Issues, https://github.com/jbj0005/snap-ocr/issues
Keywords: screenshot,ocr,tray,productivity,macos,windows
Classifier: Development Status :: 4 - Beta
Classifier: Environment :: Win32 (MS Windows)
Classifier: Environment :: MacOS X
Classifier: Intended Audience :: End Users/Desktop
Classifier: License :: OSI Approved :: MIT License
Classifier: Programming Language :: Python
Classifier: Programming Language :: Python :: 3
Classifier: Programming Language :: Python :: 3.10
Classifier: Programming Language :: Python :: 3.11
Classifier: Topic :: Utilities
Requires-Python: >=3.10
License-File: LICENSE
Requires-Dist: mss==9.0.1
Requires-Dist: pynput==1.7.6
Requires-Dist: Pillow==10.4.0
Requires-Dist: pytesseract==0.3.10
Requires-Dist: PyYAML==6.0.1
Requires-Dist: platformdirs==4.2.2
Requires-Dist: pystray==0.19.5
Requires-Dist: plyer==2.1.0
Requires-Dist: typing-extensions==4.12.2
Provides-Extra: dev
Requires-Dist: pyinstaller>=6.0; extra == "dev"
Dynamic: license-file
